scrapy_playwright_stealth/__init__.py
scrapy_playwright_stealth/handler.py
scrapy_playwright_stealth-0.1.1.dist-info/METADATA
scrapy_playwright_stealth-0.1.1.dist-info/WHEEL
scrapy_playwright_stealth-0.1.1.dist-info/licenses/LICENSE
scrapy_playwright_stealth-0.1.1.dist-info/RECORD
