Metadata-Version: 2.4
Name: scrapy-playwright-stealth
Version: 0.1.1
Summary: A wrapper for scrapy-playwright with stealth features.
Project-URL: Homepage, https://github.com/renatodvc/scrapy-playwright-stealth
Project-URL: Repository, https://github.com/renatodvc/scrapy-playwright-stealth
Author-email: renatodvc <r40128530+renatodvc@users.noreply.github.com>
License: MIT
License-File: LICENSE
Requires-Python: >=3.8
Requires-Dist: scrapy-playwright>=0.0.43
Requires-Dist: tf-playwright-stealth>=1.1.2
